MANIFEST.in
README.md
requirements.txt
setup.py
test_requirements.txt
lib/taran/__init__.py
lib/taran/foreman.py
lib/taran/starter.py
lib/taran/worker.py
lib/taran.egg-info/PKG-INFO
lib/taran.egg-info/SOURCES.txt
lib/taran.egg-info/dependency_links.txt
lib/taran.egg-info/requires.txt
lib/taran.egg-info/top_level.txt
lib/taran/activities/__init__.py
lib/taran/errors/__init__.py
lib/taran/helpers/__init__.py
lib/taran/helpers/aws/__init__.py
lib/taran/helpers/aws/clients.py
lib/taran/helpers/aws/ec2.py
lib/taran/helpers/aws/s3.py
lib/taran/helpers/aws/swf.py
lib/taran/utils/__init__.py
lib/taran/utils/aws.py
lib/taran/utils/files.py
lib/taran/utils/host.py
lib/taran/utils/service.py
lib/taran/utils/web.py
tests/__init__.py
tests/config.py
tests/test_clients.py
tests/test_helpers.py
tests/test_taran.py
tests/test_utils.py