Metadata-Version: 1.1
Name: taran
Version: 0.0.1
Summary: An orchestration framework
Home-page: https://github.com/jonhadfield/taran
Author: Jon Hadfield
Author-email: jon@lessknown.co.uk
License: MIT
Download-URL: https://github.com/jonhadfield/taran/tarball/0.0.1
Keywords: orchestration,deployment,python
Platform: any
Classifier: Development Status :: 3 - Alpha
Classifier: Natural Language :: English
Classifier: Environment :: Console
Classifier: Intended Audience :: System Administrators
Classifier: License :: OSI Approved :: MIT License
Classifier: Operating System :: OS Independent
Classifier: Topic :: System :: Operating System
Classifier: Programming Language :: Python
Classifier: Programming Language :: Python :: 2.6
Classifier: Programming Language :: Python :: 2.7
Classifier: Programming Language :: Python :: 3
Classifier: Programming Language :: Python :: 3.3
Classifier: Programming Language :: Python :: 3.4
Classifier: Programming Language :: Python :: 3.5
Classifier: Programming Language :: Python :: Implementation :: CPython
Classifier: Programming Language :: Python :: Implementation :: PyPy
